{"Response":{"allPvP":{"daily":[{"period":"2018-10-09T00:00:00Z","values":{"activitiesEntered":{"statId":"activitiesEntered","basic":{"value":4.0,"displayValue":"4"}},"activitiesWon":{"statId":"activitiesWon","basic":{"value":2.0,"displayValue":"2"}},"assists":{"statId":"assists","basic":{"value":14.0,"displayValue":"14"},"pga":{"value":3.5,"displayValue":"3.5"}},"totalDeathDistance":{"statId":"totalDeathDistance","basic":{"value":0.0,"displayValue":"0.0"}},"averageDeathDistance":{"statId":"averageDeathDistance","basic":{"value":0.0,"displayValue":"0.0"}},"totalKillDistance":{"statId":"totalKillDistance","basic":{"value":137.0,"displayValue":"137.0"}},"kills":{"statId":"kills","basic":{"value":8.0,"displayValue":"8"},"pga":{"value":2.0,"displayValue":"2.0"}},"averageKillDistance":{"statId":"averageKillDistance","basic":{"value":17.125,"displayValue":"17.1"}},"secondsPlayed":{"statId":"secondsPlayed","basic":{"value":2246.0,"displayValue":"37m 26s"},"pga":{"value":561.5,"displayValue":"9m 21s"}},"deaths":{"statId":"deaths","basic":{"value":53.0,"displayValue":"53"},"pga":{"value":13.25,"displayValue":"13.3"}},"averageLifespan":{"statId":"averageLifespan","basic":{"value":41.592592592592595,"displayValue":"0m 41s"}},"score":{"statId":"score","basic":{"value":37.0,"displayValue":"37"},"pga":{"value":9.25,"displayValue":"9"}},"averageScorePerKill":{"statId":"averageScorePerKill","basic":{"value":4.625,"displayValue":"4.63"}},"averageScorePerLife":{"statId":"averageScorePerLife","basic":{"value":0.68518518518518523,"displayValue":"0.69"}},"opponentsDefeated":{"statId":"opponentsDefeated","basic":{"value":22.0,"displayValue":"22"}},"efficiency":{"statId":"efficiency","basic":{"value":0.41509433962264153,"displayValue":"0.42"}},"killsDeathsRatio":{"statId":"killsDeathsRatio","basic":{"value":0.15094339622641509,"displayValue":"0.15"}},"killsDeathsAssists":{"statId":"killsDeathsAssists","basic":{"value":0.28301886792452829,"displayValue":"0.28"}},"maximumPowerLevel":{"statId":"maximumPowerLevel","basic":{"value":0.0,"displayValue":"0"}},"objectivesCompleted":{"statId":"objectivesCompleted","basic":{"value":5.0,"displayValue":"5"},"pga":{"value":1.25,"displayValue":"1.3"}},"precisionKills":{"statId":"precisionKills","basic":{"value":1.0,"displayValue":"1"},"pga":{"value":0.25,"displayValue":"0.3"}},"resurrectionsPerformed":{"statId":"resurrectionsPerformed","basic":{"value":0.0,"displayValue":"0"},"pga":{"value":0.0,"displayValue":"0.0"}},"resurrectionsReceived":{"statId":"resurrectionsReceived","basic":{"value":0.0,"displayValue":"0"},"pga":{"value":0.0,"displayValue":"0.0"}},"suicides":{"statId":"suicides","basic":{"value":1.0,"displayValue":"1"},"pga":{"value":0.25,"displayValue":"0.3"}},"winLossRatio":{"statId":"winLossRatio","basic":{"value":1.0,"displayValue":"1.00"}},"allParticipantsCount":{"statId":"allParticipantsCount","basic":{"value":50.0,"displayValue":"50"}},"allParticipantsScore":{"statId":"allParticipantsScore","basic":{"value":878.0,"displayValue":"878"}},"allParticipantsTimePlayed":{"statId":"allParticipantsTimePlayed","basic":{"value":26785.0,"displayValue":"7h 26m"}},"remainingTimeAfterQuitSeconds":{"statId":"remainingTimeAfterQuitSeconds","basic":{"value":0.0,"displayValue":"0m 0s"},"pga":{"value":0.0,"displayValue":"0m 0s"}},"teamScore":{"statId":"teamScore","basic":{"value":461.0,"displayValue":"461"},"pga":{"value":115.25,"displayValue":"115"}},"totalActivityDurationSeconds":{"statId":"totalActivityDurationSeconds","basic":{"value":2270.0,"displayValue":"37m 50s"},"pga":{"value":567.5,"displayValue":"9m 27s"}},"dailyMedalsEarned":{"statId":"dailyMedalsEarned","basic":{"value":24.0,"displayValue":"24"},"pga":{"value":6.0,"displayValue":"6.0"}},"combatRating":{"statId":"combatRating","basic":{"value":50.256137461282734,"displayValue":"50.26"}},"highestCharacterLevel":{"statId":"highestCharacterLevel","basic":{"value":36.0,"displayValue":"36"}},"highestLightLevel":{"statId":"highestLightLevel","basic":{"value":373.0,"displayValue":"373"}},"highestSandboxLevel":{"statId":"highestSandboxLevel","basic":{"value":36.0,"displayValue":"36"}},"fireTeamActivities":{"statId":"fireTeamActivities","basic":{"value":0.0,"displayValue":"0"}}}}]}},"ErrorCode":1,"ThrottleSeconds":0,"ErrorStatus":"Success","Message":"Ok","MessageData":{}}